gocept/__init__.py
gocept/rdbmanagement/__init__.py
gocept/rdbmanagement/recipe.py
gocept.rdbmanagement-1.1.dist-info/METADATA
gocept.rdbmanagement-1.1.dist-info/WHEEL
gocept.rdbmanagement-1.1.dist-info/entry_points.txt
gocept.rdbmanagement-1.1.dist-info/top_level.txt
gocept.rdbmanagement-1.1.dist-info/RECORD
