Metadata-Version: 2.1
Name: gocept.rdbmanagement
Version: 1.1
Summary: Recipe for managing RDB schemas
Home-page: http://pypi.python.org/pypi/gocept.rdbmanagement
Author: Michael Howitz
Author-email: mail@gocept.com
License: ZPL 2.1
Keywords: buildout rdb
Platform: UNKNOWN
Classifier: Framework :: Buildout
Classifier: Development Status :: 3 - Alpha
Classifier: Topic :: Database
Classifier: Environment :: Console
Classifier: Intended Audience :: Developers
Classifier: License :: OSI Approved :: Zope Public License
Classifier: Operating System :: Unix
Classifier: Programming Language :: Python
Classifier: Programming Language :: Python :: 2
Classifier: Programming Language :: Python :: 2.7
Classifier: Programming Language :: Python :: 3
Classifier: Programming Language :: Python :: 3.7
Classifier: Programming Language :: Python :: 3.8
Requires-Dist: zc.buildout
Requires-Dist: setuptools
Requires-Dist: psycopg2 (>=2.0.6)
Requires-Dist: zc.recipe.egg
